mnt/CMakeLists.txt
mnt/__init__.py
mnt/pyfiction/CMakeLists.txt
mnt/pyfiction/README.md
mnt/pyfiction/__init__.py
mnt/pyfiction/pyfiction.cpython-313-aarch64-linux-gnu.so
mnt_pyfiction.libs/libz3-94999a8b.so.4.15
mnt_pyfiction-0.6.11.dist-info/METADATA
mnt_pyfiction-0.6.11.dist-info/WHEEL
mnt_pyfiction-0.6.11.dist-info/RECORD
mnt_pyfiction-0.6.11.dist-info/licenses/LICENSE.txt
