Metadata-Version: 2.1
Name: mnt.pyfiction
Version: 0.6.11
Summary: Design Automation for Field-coupled Nanotechnologies
Keywords: MNT,fiction,nanotechnology,FCN,QCA,NML,SiDB,design automation,placement,routing,clocking,simulation
Author-Email: Marcel Walter <marcel.walter@tum.de>, Jan Drewniok <jan.drewniok@tum.de>, Simon Hofmann <simon.t.hofmann@tum.de>, Benjamin Hien <benjamin.hien@tum.de>, Willem Lambooy <willem.lambooy@tum.de>
License: Copyright 2018-2023 Marcel Walter
Classifier: Development Status :: 4 - Beta
Classifier: Programming Language :: Python :: 3
Classifier: Programming Language :: Python :: 3 :: Only
Classifier: Programming Language :: Python :: 3.9
Classifier: Programming Language :: Python :: 3.10
Classifier: Programming Language :: Python :: 3.11
Classifier: Programming Language :: Python :: 3.12
Classifier: Programming Language :: Python :: 3.13
Classifier: Programming Language :: C++
Classifier: Environment :: Console
Classifier: License :: OSI Approved :: MIT License
Classifier: Operating System :: Microsoft :: Windows
Classifier: Operating System :: MacOS
Classifier: Operating System :: POSIX :: Linux
Classifier: Intended Audience :: Science/Research
Classifier: Natural Language :: English
Classifier: Topic :: Scientific/Engineering :: Electronic Design Automation (EDA)
Project-URL: Source, https://github.com/cda-tum/fiction
Project-URL: Tracker, https://github.com/cda-tum/fiction/issues
Project-URL: Documentation, https://fiction.readthedocs.io/en/latest/
Project-URL: Research, https://www.cda.cit.tum.de/research/fcn/
Requires-Python: >=3.9
Requires-Dist: z3-solver>=4.8.0
Provides-Extra: test
Requires-Dist: pytest>=7.2; extra == "test"
Requires-Dist: mnt.pyfiction; extra == "test"
